streamxx_common/__init__.py
streamxx_common/auth/__init__.py
streamxx_common/auth/exceptions.py
streamxx_common/auth/kc_token_validation.py
streamxx_common-0.1.1.dist-info/METADATA
streamxx_common-0.1.1.dist-info/WHEEL
streamxx_common-0.1.1.dist-info/RECORD
