Metadata-Version: 2.3
Name: streamxx-common
Version: 0.1.1
Summary: 
Author: Rinat Kurbanov
Author-email: frendjoy55@gmail.com
Requires-Python: >=3.11.9,<4.0.0
Classifier: Programming Language :: Python :: 3
Classifier: Programming Language :: Python :: 3.12
Classifier: Programming Language :: Python :: 3.13
Requires-Dist: fastapi (>=0.115.6,<0.116.0)
Requires-Dist: jwcrypto (>=1.5.6,<2.0.0)
Requires-Dist: python-keycloak (>=5.1.1,<6.0.0)
Requires-Dist: redis (>=5.2.1,<6.0.0)
